{
    "position1": {
        "detailLink": "position_detail.php?id=31079&keywords=&tid=0&lid=0",
        "catalog": "技术类",
        "name": "MIG16-地图数据机器学习算法高级研发工程师（北京）"
    },
    "position2": {
        "detailLink": "position_detail.php?id=31951&keywords=&tid=0&lid=0",
        "catalog": "技术类",
        "name": "MIG16-腾讯位置服务开放平台web前端工程师（北京）"
    },
    "position3": {
        "detailLink": "position_detail.php?id=32464&keywords=&tid=0&lid=0",
        "catalog": "技术类",
        "name": "MIG16-地图检索机器学习算法高级研发工程师（北京）"
    },
    "position4": {
        "detailLink": "position_detail.php?id=33075&keywords=&tid=0&lid=0",
        "catalog": "产品/项目类",
        "name": "MIG16-腾讯位置服务产品经理（北京）"
    },
    "position5": {
        "detailLink": "position_detail.php?id=33490&keywords=&tid=0&lid=0",
        "catalog": "技术类",
        "name": "MIG16-地图大数据平台开发工程师(北京)"
    },
    "position6": {
        "detailLink": "position_detail.php?id=33494&keywords=&tid=0&lid=0",
        "catalog": "技术类",
        "name": "MIG16-计算机视觉高级算法工程师（北京）"
    },
    "position7": {
        "detailLink": "position_detail.php?id=33571&keywords=&tid=0&lid=0",
        "catalog": "技术类",
        "name": "MIG16-后台高级研发工程师（北京）"
    },
    "position8": {
        "detailLink": "position_detail.php?id=33572&keywords=&tid=0&lid=0",
        "catalog": "技术类",
        "name": "MIG16-地图数据后台开发工程师(北京)"
    },
    "position9": {
        "detailLink": "position_detail.php?id=33582&keywords=&tid=0&lid=0",
        "catalog": "技术类",
        "name": "MIG16-地图高级质量工程师（北京）"
    },
    "position10": {
        "detailLink": "position_detail.php?id=33583&keywords=&tid=0&lid=0",
        "catalog": "技术类",
        "name": "MIG16-地图质量工程师（北京）"
    }
}